pypanda/capability/github/__init__.py
pypanda/capability/github/instance.py
pypanda/capability/jira/JiraManager.py
pypanda/capability/jira/JiraSchema.py
pypanda/capability/jira/ServiceDeskManager.py
pypanda/capability/jira/__init__.py
pypanda/capability/jira/core/JiraFormRest.py
pypanda/capability/jira/core/JiraRest.py
pypanda/capability/jira/core/JiraSession.py
pypanda/capability/jira/core/ServiceDeskRest.py
pypanda/capability/jira/core/__init__.py
pypanda/capability/kubernetes/Config.py
pypanda/capability/kubernetes/Kube.py
pypanda/capability/kubernetes/__init__.py
pypanda/capability/utils/__init__.py
pypanda/capability/utils/fintool.py
pypanda/capability/utils/isip.py
pypanda/capability/utils/mail_client.py
pypanda_capability-0.1.5.dist-info/METADATA
pypanda_capability-0.1.5.dist-info/WHEEL
pypanda_capability-0.1.5.dist-info/RECORD
